telegram_auto_translate/__init__.py
telegram_auto_translate/__main__.py
telegram_auto_translate-0.1.10.dist-info/METADATA
telegram_auto_translate-0.1.10.dist-info/WHEEL
telegram_auto_translate-0.1.10.dist-info/entry_points.txt
telegram_auto_translate-0.1.10.dist-info/licenses/LICENSE
telegram_auto_translate-0.1.10.dist-info/RECORD
