Metadata-Version: 2.4
Name: telegram-auto-translate
Version: 0.1.10
Summary: Telegram userbot that automatically translates outgoing messages using Claude and GPT
Project-URL: Homepage, https://github.com/aimoda/telegram-auto-translate
Project-URL: Repository, https://github.com/aimoda/telegram-auto-translate
Project-URL: Issues, https://github.com/aimoda/telegram-auto-translate/issues
Author: ai.moda
License-Expression: MIT
License-File: LICENSE
Keywords: anthropic,auto-translate,bedrock,claude,openai,telegram,telethon,translation,userbot
Classifier: Development Status :: 4 - Beta
Classifier: Intended Audience :: Developers
Classifier: License :: OSI Approved :: MIT License
Classifier: Programming Language :: Python :: 3
Classifier: Programming Language :: Python :: 3.10
Classifier: Programming Language :: Python :: 3.11
Classifier: Programming Language :: Python :: 3.12
Classifier: Programming Language :: Python :: 3.13
Classifier: Topic :: Communications :: Chat
Classifier: Topic :: Text Processing :: Linguistic
Requires-Python: >=3.10
Requires-Dist: anthropic[bedrock]
Requires-Dist: azure-identity
Requires-Dist: httpx[http2]
Requires-Dist: openai
Requires-Dist: pydantic
Requires-Dist: telethon
